ask_sdk_core/__init__.py
ask_sdk_core/__version__.py
ask_sdk_core/api_client.py
ask_sdk_core/attributes_manager.py
ask_sdk_core/exceptions.py
ask_sdk_core/handler_input.py
ask_sdk_core/py.typed
ask_sdk_core/response_helper.py
ask_sdk_core/serialize.py
ask_sdk_core/skill.py
ask_sdk_core/skill_builder.py
ask_sdk_core/dispatch_components/__init__.py
ask_sdk_core/dispatch_components/exception_components.py
ask_sdk_core/dispatch_components/py.typed
ask_sdk_core/dispatch_components/request_components.py
ask_sdk_core/utils/__init__.py
ask_sdk_core/utils/predicate.py
ask_sdk_core/utils/py.typed
ask_sdk_core/utils/request_util.py
ask_sdk_core/utils/view_resolver.py
ask_sdk_core/utils/viewport.py
ask_sdk_core/view_resolvers/__init__.py
ask_sdk_core/view_resolvers/access_ordered_template_content.py
ask_sdk_core/view_resolvers/file_system_template_loader.py
ask_sdk_core/view_resolvers/locale_template_enumerator.py
ask_sdk_core/view_resolvers/lru_cache.py
ask_sdk_core/view_resolvers/py.typed
ask_sdk_core/view_resolvers/template_content.py
ask_sdk_core/view_resolvers/template_factory.py
ask_sdk_core-1.19.0.dist-info/METADATA
ask_sdk_core-1.19.0.dist-info/WHEEL
ask_sdk_core-1.19.0.dist-info/top_level.txt
ask_sdk_core-1.19.0.dist-info/RECORD
